asyncpixel-1.7.0.dist-info/METADATA
asyncpixel-1.7.0.dist-info/WHEEL
asyncpixel-1.7.0.dist-info/licenses/LICENSE
asyncpixel/.DS_Store
asyncpixel/__init__.py
asyncpixel/constants.py
asyncpixel/exceptions/__init__.py
asyncpixel/exceptions/exceptions.py
asyncpixel/hypixel.py
asyncpixel/hypixelconstants/.gitattributes
asyncpixel/hypixelconstants/.github/workflows/autoupdater.yml
asyncpixel/hypixelconstants/.gitignore
asyncpixel/hypixelconstants/LICENSE
asyncpixel/hypixelconstants/README.md
asyncpixel/hypixelconstants/build/achievements.json
asyncpixel/hypixelconstants/build/achievements_extended.json
asyncpixel/hypixelconstants/build/challenges.json
asyncpixel/hypixelconstants/build/game_types.json
asyncpixel/hypixelconstants/build/guild_achievements.json
asyncpixel/hypixelconstants/build/languages.json
asyncpixel/hypixelconstants/build/maps.json
asyncpixel/hypixelconstants/build/modes.json
asyncpixel/hypixelconstants/build/pet_xp.json
asyncpixel/hypixelconstants/build/quests.json
asyncpixel/hypixelconstants/build/skyblock_bazaar.json
asyncpixel/hypixelconstants/build/skyblock_collections.json
asyncpixel/hypixelconstants/build/skyblock_items.json
asyncpixel/hypixelconstants/build/skyblock_skills.json
asyncpixel/hypixelconstants/index.js
asyncpixel/hypixelconstants/json/game_types.json
asyncpixel/hypixelconstants/json/languages.json
asyncpixel/hypixelconstants/json/maps.json
asyncpixel/hypixelconstants/json/pet_xp.json
asyncpixel/hypixelconstants/json/skyblock_bazaar.json
asyncpixel/hypixelconstants/package-lock.json
asyncpixel/hypixelconstants/package.json
asyncpixel/hypixelconstants/tasks/updateconstants.js
asyncpixel/models/__init__.py
asyncpixel/models/auctions.py
asyncpixel/models/auctions_ended.py
asyncpixel/models/bazaar.py
asyncpixel/models/booster.py
asyncpixel/models/friends.py
asyncpixel/models/game_count.py
asyncpixel/models/games.py
asyncpixel/models/guild.py
asyncpixel/models/key.py
asyncpixel/models/leaderboards.py
asyncpixel/models/news.py
asyncpixel/models/pet.py
asyncpixel/models/player.py
asyncpixel/models/player_profile.py
asyncpixel/models/players/__init__.py
asyncpixel-1.7.0.dist-info/RECORD
