Metadata-Version: 2.1
Name: asyncpixel
Version: 1.7.0
Summary: Asynchronous Python library for the Hypixel API
Author-Email: Leon Bowie <leon@bowie-co.nz>
License: GPL-3.0-or-later
Classifier: Development Status :: 5 - Production/Stable
Classifier: Natural Language :: English
Classifier: Framework :: AsyncIO
Classifier: Operating System :: OS Independent
Classifier: Topic :: Games/Entertainment
Classifier: Topic :: Software Development :: Libraries
Classifier: Topic :: Software Development :: Libraries :: Python Modules
Classifier: Topic :: Utilities
Classifier: Programming Language :: Python :: 3
Classifier: Programming Language :: Python :: 3.8
Classifier: Programming Language :: Python :: 3.9
Classifier: Programming Language :: Python :: 3.10
Classifier: Programming Language :: Python :: 3.11
Project-URL: Homepage, https://asyncpixel.readthedocs.io
Project-URL: Repository, https://github.com/Darkflame72/asyncpixel
Project-URL: Documentation, https://asyncpixel.readthedocs.io
Requires-Python: >=3.8.1
Requires-Dist: aiohttp>=3.8.5
Requires-Dist: pydantic>=2.2.1
